{
	"info": {
		"_postman_id": "ccc1db36-c143-455c-9051-545311cb8f42",
		"name": "HH-back API",
		"description": "api testing",
		"schema": "https://schema.getpostman.com/json/collection/v2.1.0/collection.json",
		"_exporter_id": "43787003",
		"_collection_link": "https://meaqqlee.postman.co/workspace/meaqqlee's-Workspace~e5fa2c87-9342-4df6-8b89-383e09e70b15/collection/43787003-ccc1db36-c143-455c-9051-545311cb8f42?action=share&source=collection_link&creator=43787003"
	},
	"item": [
		{
			"name": "Get All Companies",
			"request": {
				"method": "GET",
				"header": [],
				"url": {
					"raw": "http://localhost:8000/api/companies",
					"protocol": "http",
					"host": [
						"localhost"
					],
					"port": "8000",
					"path": [
						"api",
						"companies"
					]
				}
			},
			"response": []
		},
		{
			"name": "Get Single Company",
			"request": {
				"auth": {
					"type": "noauth"
				},
				"method": "GET",
				"header": [],
				"url": {
					"raw": "http://localhost:8000/api/companies/1/",
					"protocol": "http",
					"host": [
						"localhost"
					],
					"port": "8000",
					"path": [
						"api",
						"companies",
						"1",
						""
					]
				}
			},
			"response": []
		},
		{
			"name": "Get Company Vacancies",
			"request": {
				"auth": {
					"type": "noauth"
				},
				"method": "GET",
				"header": [],
				"url": {
					"raw": "http://localhost:8000/api/companies/2/vacancies/",
					"protocol": "http",
					"host": [
						"localhost"
					],
					"port": "8000",
					"path": [
						"api",
						"companies",
						"2",
						"vacancies",
						""
					]
				}
			},
			"response": []
		},
		{
			"name": "\"Get All Vacancies",
			"request": {
				"auth": {
					"type": "noauth"
				},
				"method": "GET",
				"header": [],
				"url": {
					"raw": "http://localhost:8000/api/vacancies/",
					"protocol": "http",
					"host": [
						"localhost"
					],
					"port": "8000",
					"path": [
						"api",
						"vacancies",
						""
					]
				}
			},
			"response": []
		},
		{
			"name": "Get Single Vacancy",
			"request": {
				"auth": {
					"type": "noauth"
				},
				"method": "GET",
				"header": [],
				"url": {
					"raw": "http://localhost:8000/api/vacancies/1/",
					"protocol": "http",
					"host": [
						"localhost"
					],
					"port": "8000",
					"path": [
						"api",
						"vacancies",
						"1",
						""
					]
				}
			},
			"response": []
		},
		{
			"name": "Get Top Ten Vacancies",
			"request": {
				"auth": {
					"type": "noauth"
				},
				"method": "GET",
				"header": [],
				"url": {
					"raw": "http://localhost:8000/api/vacancies/top_ten/",
					"protocol": "http",
					"host": [
						"localhost"
					],
					"port": "8000",
					"path": [
						"api",
						"vacancies",
						"top_ten",
						""
					]
				}
			},
			"response": []
		}
	]
}